streamlit_google_geochart/__init__.py
streamlit_google_geochart/frontend/build/asset-manifest.json
streamlit_google_geochart/frontend/build/index.html
streamlit_google_geochart/frontend/build/static/js/2.6bebf3b6.chunk.js
streamlit_google_geochart/frontend/build/static/js/2.6bebf3b6.chunk.js.LICENSE.txt
streamlit_google_geochart/frontend/build/static/js/2.6bebf3b6.chunk.js.map
streamlit_google_geochart/frontend/build/static/js/2.ff922e3d.chunk.js
streamlit_google_geochart/frontend/build/static/js/2.ff922e3d.chunk.js.LICENSE.txt
streamlit_google_geochart/frontend/build/static/js/2.ff922e3d.chunk.js.map
streamlit_google_geochart/frontend/build/static/js/main.de9c3825.chunk.js
streamlit_google_geochart/frontend/build/static/js/main.de9c3825.chunk.js.map
streamlit_google_geochart/frontend/build/static/js/main.f1f85ef1.chunk.js
streamlit_google_geochart/frontend/build/static/js/main.f1f85ef1.chunk.js.map
streamlit_google_geochart/frontend/build/static/js/runtime-main.c6cc7828.js
streamlit_google_geochart/frontend/build/static/js/runtime-main.c6cc7828.js.map
streamlit_google_geochart-0.0.2.dist-info/METADATA
streamlit_google_geochart-0.0.2.dist-info/WHEEL
streamlit_google_geochart-0.0.2.dist-info/top_level.txt
streamlit_google_geochart-0.0.2.dist-info/RECORD
