Metadata-Version: 2.1
Name: streamlit-google-geochart
Version: 0.0.2
Summary: Create a Google Geochart for Streamlit
Home-page: UNKNOWN
Author: 
Author-email: 
License: UNKNOWN
Platform: UNKNOWN
Requires-Python: >=3.6
Requires-Dist: streamlit (>=0.63)
